promsoft_weight_calc_interface/__init__.py
promsoft_weight_calc_interface/models.py
promsoft_weight_calc_interface-0.2.4.dist-info/METADATA
promsoft_weight_calc_interface-0.2.4.dist-info/WHEEL
promsoft_weight_calc_interface-0.2.4.dist-info/RECORD
