Metadata-Version: 2.1
Name: promsoft_weight_calc_interface
Version: 0.2.4
Summary: An interface for weight_calc service.
Author: Alena Chegodaikina
Author-email: alena@promsoft.ru
Requires-Python: >=3.10,<4.0
Classifier: Programming Language :: Python :: 3
Classifier: Programming Language :: Python :: 3.10
Classifier: Programming Language :: Python :: 3.11
Classifier: Programming Language :: Python :: 3.12
Requires-Dist: pydantic (>=1.10.12,<2.0.0)
